cyberOffensive/Linux_and_MAC.py
cyberOffensive/__init__.py
cyberOffensive/cors.py
cyberOffensive/native/__init__.py
cyberOffensive/native/windows_func.pyd
cyberOffensive/platforms/Linux.py
cyberOffensive/platforms/MAC.py
cyberOffensive/platforms/Windows.py
cyberOffensive/platforms/__init__.py
cyberoffensive-0.0.5.dist-info/licenses/License
cyberoffensive-0.0.5.dist-info/METADATA
cyberoffensive-0.0.5.dist-info/WHEEL
cyberoffensive-0.0.5.dist-info/top_level.txt
cyberoffensive-0.0.5.dist-info/RECORD
