Metadata-Version: 2.4
Name: cyberOffensive
Version: 0.0.5
Summary: Educational cross-platform system toolkit! Mainly windows focused!
Author-email: Arpit Jaiswal <arpitjaiswal9526@gmail.com>
License: The MIT License (MIT)
Classifier: License :: OSI Approved :: MIT License
Requires-Python: >=3.9
License-File: License
Requires-Dist: requests
Requires-Dist: psutil
Dynamic: license-file
